Metadata-Version: 2.1
Name: acAutoMechine
Version: 0.0.3
Summary: A fast Python implementation of ac auto mechine.
Home-page: https://github.com/jinzitian/AcAutoMechine
Author: Chef_J
Author-email: hedge_jzt@hotmail.com
Maintainer: Chef_J
Maintainer-email: hedge_jzt@hotmail.com
License: MIT
Platform: UNKNOWN
Classifier: Intended Audience :: Developers
Classifier: License :: OSI Approved :: MIT License
Classifier: Operating System :: OS Independent
Classifier: Programming Language :: Python
Classifier: Programming Language :: Python :: 3
Classifier: Topic :: Software Development :: Libraries
License-File: LICENSE.txt
